{"d47b3316f958ad5f4e040ba9455f262c":{"statistic":{"failed":0,"broken":0,"skipped":0,"passed":1,"unknown":0,"total":1},"items":[{"uid":"c273c074eaa2915d","reportUrl":"https://iinj.github.io/autotests-ui/6//#testresult/c273c074eaa2915d","status":"passed","time":{"start":1756218663630,"stop":1756218663630,"duration":0}}]},"c887e030d98c88ac65a606be7411ef2e":{"statistic":{"failed":0,"broken":0,"skipped":0,"passed":1,"unknown":0,"total":1},"items":[{"uid":"ed60fe2d36b190f7","reportUrl":"https://iinj.github.io/autotests-ui/6//#testresult/ed60fe2d36b190f7","status":"passed","time":{"start":1756218663646,"stop":1756218663647,"duration":1}}]},"d8c505e45a0342d1f1291ba827195fda":{"statistic":{"failed":0,"broken":0,"skipped":0,"passed":1,"unknown":0,"total":1},"items":[{"uid":"4fc7b7745d385611","reportUrl":"https://iinj.github.io/autotests-ui/6//#testresult/4fc7b7745d385611","status":"passed","time":{"start":1756218656817,"stop":1756218658124,"duration":1307}}]},"1ac91e93209424695453f5bd9839e52d":{"statistic":{"failed":0,"broken":0,"skipped":0,"passed":1,"unknown":0,"total":1},"items":[{"uid":"18eb73f63737b926","reportUrl":"https://iinj.github.io/autotests-ui/6//#testresult/18eb73f63737b926","status":"passed","time":{"start":1756218661720,"stop":1756218664470,"duration":2750}}]},"286be676f5f59009ab00966f91528b11":{"statistic":{"failed":0,"broken":0,"skipped":0,"passed":1,"unknown":0,"total":1},"items":[{"uid":"b387de6017a3825a","reportUrl":"https://iinj.github.io/autotests-ui/6//#testresult/b387de6017a3825a","status":"passed","time":{"start":1756218656226,"stop":1756218657718,"duration":1492}}]},"4eff3ab65cbfee2d7a4f9afa9de3d5b8":{"statistic":{"failed":0,"broken":0,"skipped":0,"passed":1,"unknown":0,"total":1},"items":[{"uid":"26b4d8c9b959816b","reportUrl":"https://iinj.github.io/autotests-ui/6//#testresult/26b4d8c9b959816b","status":"passed","time":{"start":1756218652747,"stop":1756218654467,"duration":1720}}]},"ca8e4005ae6743a7222896e350ca43ee":{"statistic":{"failed":0,"broken":0,"skipped":0,"passed":1,"unknown":0,"total":1},"items":[{"uid":"dd13a00c68e5eb77","reportUrl":"https://iinj.github.io/autotests-ui/6//#testresult/dd13a00c68e5eb77","status":"passed","time":{"start":1756218663656,"stop":1756218663656,"duration":0}}]},"18e044e52be5dd8e37ea09785c7c2820":{"statistic":{"failed":0,"broken":0,"skipped":0,"passed":1,"unknown":0,"total":1},"items":[{"uid":"4d4f5d66bac6758c","reportUrl":"https://iinj.github.io/autotests-ui/6//#testresult/4d4f5d66bac6758c","status":"passed","time":{"start":1756218659305,"stop":1756218661647,"duration":2342}}]},"8b96ff728ee484169780257b0eef330c":{"statistic":{"failed":0,"broken":0,"skipped":0,"passed":1,"unknown":0,"total":1},"items":[{"uid":"aaa299fe8125affc","reportUrl":"https://iinj.github.io/autotests-ui/6//#testresult/aaa299fe8125affc","status":"passed","time":{"start":1756218663652,"stop":1756218663652,"duration":0}}]},"6f43f9e252940c24500c899b6fa77769":{"statistic":{"failed":0,"broken":0,"skipped":0,"passed":1,"unknown":0,"total":1},"items":[{"uid":"6fec7d231022af49","reportUrl":"https://iinj.github.io/autotests-ui/6//#testresult/6fec7d231022af49","status":"passed","time":{"start":1756218652747,"stop":1756218655886,"duration":3139}}]},"f3d0c0b133a6a6ced1f6105c675e0bf4":{"statistic":{"failed":0,"broken":0,"skipped":0,"passed":1,"unknown":0,"total":1},"items":[{"uid":"1a8428628bc8eea7","reportUrl":"https://iinj.github.io/autotests-ui/6//#testresult/1a8428628bc8eea7","status":"passed","time":{"start":1756218658324,"stop":1756218659909,"duration":1585}}]},"285e2ddca4f920412b09d48f20bed789":{"statistic":{"failed":0,"broken":0,"skipped":0,"passed":1,"unknown":0,"total":1},"items":[{"uid":"c1e59c7f67f0619c","reportUrl":"https://iinj.github.io/autotests-ui/6//#testresult/c1e59c7f67f0619c","status":"passed","time":{"start":1756218654895,"stop":1756218656574,"duration":1679}}]},"2665a68cc041e66979fef8ac01824763":{"statistic":{"failed":0,"broken":0,"skipped":0,"passed":1,"unknown":0,"total":1},"items":[{"uid":"db7b9af1722801b7","reportUrl":"https://iinj.github.io/autotests-ui/6//#testresult/db7b9af1722801b7","status":"passed","time":{"start":1756218664896,"stop":1756218666415,"duration":1519}}]},"8f3b2a73e85056bb5a43c5581514322c":{"statistic":{"failed":0,"broken":0,"skipped":0,"passed":1,"unknown":0,"total":1},"items":[{"uid":"fdb88b84f9d1c913","reportUrl":"https://iinj.github.io/autotests-ui/6//#testresult/fdb88b84f9d1c913","status":"passed","time":{"start":1756218663637,"stop":1756218663637,"duration":0}}]},"1d1334675366209fc2d6be27b93140d3":{"statistic":{"failed":0,"broken":0,"skipped":0,"passed":1,"unknown":0,"total":1},"items":[{"uid":"1c5ccf1fe9d917de","reportUrl":"https://iinj.github.io/autotests-ui/6//#testresult/1c5ccf1fe9d917de","status":"passed","time":{"start":1756218663642,"stop":1756218663642,"duration":0}}]},"52819afde9c88e9964383828876debff":{"statistic":{"failed":0,"broken":0,"skipped":0,"passed":1,"unknown":0,"total":1},"items":[{"uid":"ac7f3c403c777e3a","reportUrl":"https://iinj.github.io/autotests-ui/6//#testresult/ac7f3c403c777e3a","status":"passed","time":{"start":1756218662066,"stop":1756218663506,"duration":1440}}]}}